nativemessaging/__init__.py
nativemessaging-1.0.1.data/scripts/nativemessaging-install.py
nativemessaging-1.0.1.dist-info/DESCRIPTION.rst
nativemessaging-1.0.1.dist-info/METADATA
nativemessaging-1.0.1.dist-info/RECORD
nativemessaging-1.0.1.dist-info/WHEEL
nativemessaging-1.0.1.dist-info/metadata.json
nativemessaging-1.0.1.dist-info/top_level.txt
