Metadata-Version: 2.1
Name: nativemessaging
Version: 1.0.1
Summary: A package with basic native messaging apis for webextensions
Home-page: https://github.com/Rayquaza01/nativemessaging
Author: Rayquaza01
Author-email: rayquaza01@outlook.com
License: MPL 2.0
Platform: UNKNOWN
Classifier: Programming Language :: Python :: 3
Classifier: License :: OSI Approved :: Mozilla Public License 2.0 (MPL 2.0)
Classifier: Operating System :: OS Independent
